Serializers/__init__.py
Serializers/base_serializer.py
Serializers/dict_serializer.py
Serializers/json_serializer.py
Serializers/serializers_factory.py
Serializers/type_constants.py
Serializers/xml_serializer.py
KosminSerializer-1.0.dist-info/METADATA
KosminSerializer-1.0.dist-info/WHEEL
KosminSerializer-1.0.dist-info/top_level.txt
KosminSerializer-1.0.dist-info/RECORD
