Metadata-Version: 2.1
Name: KosminSerializer
Version: 1.0
Summary: module for python serialization(JSON, XML)
Home-page: https://github.com/kosmp/SCol_labs/tree/lab3
Author: Pavel Kosmin
Author-email: kosmin.2003@mail.ru
License: UNKNOWN
Platform: UNKNOWN
Classifier: Intended Audience :: Developers
Classifier: Programming Language :: Python :: 3.10
Classifier: Operating System :: OS Independent
